eolib/__about__.py
eolib/__init__.py
eolib/py.typed
eolib/data/__init__.py
eolib/data/eo_numeric_limits.py
eolib/data/eo_reader.py
eolib/data/eo_writer.py
eolib/data/number_encoding_utils.py
eolib/data/string_encoding_utils.py
eolib/encrypt/__init__.py
eolib/encrypt/encryption_utils.py
eolib/encrypt/server_verification_utils.py
eolib/packet/__init__.py
eolib/packet/packet_sequencer.py
eolib/packet/sequence_start.py
eolib/protocol/__init__.py
eolib/protocol/protocol_enum_meta.py
eolib/protocol/serialization_error.py
eolib/protocol/_generated/__init__.py
eolib/protocol/_generated/admin_level.py
eolib/protocol/_generated/coords.py
eolib/protocol/_generated/direction.py
eolib/protocol/_generated/emote.py
eolib/protocol/_generated/gender.py
eolib/protocol/_generated/map/__init__.py
eolib/protocol/_generated/map/emf.py
eolib/protocol/_generated/map/map_graphic_layer.py
eolib/protocol/_generated/map/map_graphic_row.py
eolib/protocol/_generated/map/map_graphic_row_tile.py
eolib/protocol/_generated/map/map_item.py
eolib/protocol/_generated/map/map_legacy_door_key.py
eolib/protocol/_generated/map/map_music_control.py
eolib/protocol/_generated/map/map_npc.py
eolib/protocol/_generated/map/map_sign.py
eolib/protocol/_generated/map/map_tile_spec.py
eolib/protocol/_generated/map/map_tile_spec_row.py
eolib/protocol/_generated/map/map_tile_spec_row_tile.py
eolib/protocol/_generated/map/map_timed_effect.py
eolib/protocol/_generated/map/map_type.py
eolib/protocol/_generated/map/map_warp.py
eolib/protocol/_generated/map/map_warp_row.py
eolib/protocol/_generated/map/map_warp_row_tile.py
eolib/protocol/_generated/net/__init__.py
eolib/protocol/_generated/net/char_item.py
eolib/protocol/_generated/net/item.py
eolib/protocol/_generated/net/packet_action.py
eolib/protocol/_generated/net/packet_family.py
eolib/protocol/_generated/net/party_request_type.py
eolib/protocol/_generated/net/quest_page.py
eolib/protocol/_generated/net/spell.py
eolib/protocol/_generated/net/three_item.py
eolib-2.0.2.dist-info/METADATA
eolib-2.0.2.dist-info/WHEEL
eolib-2.0.2.dist-info/licenses/LICENSE.txt
eolib-2.0.2.dist-info/RECORD
