Metadata-Version: 2.4
Name: eolib
Version: 2.0.2
Summary: Core library for writing applications related to Endless Online.
Project-URL: Documentation, https://cirras.github.io/eolib-python
Project-URL: Issues, https://github.com/Cirras/eolib-python/issues
Project-URL: Source, https://github.com/Cirras/eolib-python
Author-email: Jonah Jeleniewski <cirrasbu@hotmail.com>
License-Expression: MIT
License-File: LICENSE.txt
Keywords: endless-online
Classifier: Development Status :: 5 - Production/Stable
Classifier: Programming Language :: Python
Classifier: Programming Language :: Python :: 3.8
Classifier: Programming Language :: Python :: 3.9
Classifier: Programming Language :: Python :: 3.10
Classifier: Programming Language :: Python :: 3.11
Classifier: Programming Language :: Python :: 3.12
Classifier: Programming Language :: Python :: 3.13
Classifier: Programming Language :: Python :: 3.14
Classifier: Programming Language :: Python :: Implementation :: CPython
Classifier: Programming Language :: Python :: Implementation :: PyPy
Classifier: Topic :: Games/Entertainment
Requires-Python: >=3.8
